QKDSimkit/Channel.py
QKDSimkit/Client.py
QKDSimkit/Server.py
QKDSimkit/__init__.py
QKDSimkit/cli.py
QKDSimkit/p2p_servers.py
QKDSimkit/core/__init__.py
QKDSimkit/core/alice.py
QKDSimkit/core/bob.py
QKDSimkit/core/channel.py
QKDSimkit/core/channel_features.py
QKDSimkit/core/models.py
QKDSimkit/core/node.py
QKDSimkit/core/qexceptions.py
QKDSimkit/core/receiver.py
QKDSimkit/core/sender.py
QKDSimkit/core/utils.py
QKDSimkit-0.0.7.dist-info/LICENSE
QKDSimkit-0.0.7.dist-info/METADATA
QKDSimkit-0.0.7.dist-info/WHEEL
QKDSimkit-0.0.7.dist-info/entry_points.txt
QKDSimkit-0.0.7.dist-info/top_level.txt
QKDSimkit-0.0.7.dist-info/RECORD
