Metadata-Version: 2.1
Name: QKDSimkit
Version: 0.0.7
Summary: Quantum Key Distribution simulator
Home-page: https://github.com/CERN/Quantumacy/tree/main/QKDSimkit
Author: Alberto Di Meglio and Gabriele Morello
Author-email: gabriele.morello@cern.ch
License: MIT License
Project-URL: Bug Tracker, https://github.com/CERN/Quantumacy/issues
Platform: UNKNOWN
Classifier: License :: OSI Approved :: MIT License
Classifier: Operating System :: Unix
Requires-Python: >=3.8
License-File: LICENSE
Requires-Dist: cryptography (==36.0.1)
Requires-Dist: fastapi[all]
Requires-Dist: aiocache[memcached,redis]
Requires-Dist: aioredis (==1.3.1)
Requires-Dist: aioredlock (==0.7.3)
Requires-Dist: msgpack (==1.0.3)
